llm_voice/__init__.py
llm_voice/env.py
llm_voice/errors/__init__.py
llm_voice/errors/invalid_log_level_error.py
llm_voice/errors/respond_error.py
llm_voice/interfaces/__init__.py
llm_voice/interfaces/audio_device.py
llm_voice/interfaces/pyaudio_device_info.py
llm_voice/llm/__init__.py
llm_voice/llm/base.py
llm_voice/llm/ollama_client.py
llm_voice/llm/openai_client.py
llm_voice/responder/__init__.py
llm_voice/responder/responder.py
llm_voice/responder/voice_responder_fast.py
llm_voice/responder/voice_responder_normal.py
llm_voice/tts/__init__.py
llm_voice/tts/apple_say_text_to_speech_client.py
llm_voice/tts/base.py
llm_voice/tts/eleven_labs_text_to_speech_client.py
llm_voice/tts/google_cloud_text_to_speech_client.py
llm_voice/tts/google_text_to_speech_client.py
llm_voice/tts/openai_text_to_speech_client.py
llm_voice/utils/__init__.py
llm_voice/utils/audio_devices.py
llm_voice/utils/logger.py
llm_voice/utils/mp3_file.py
llm_voice-0.0.1.dist-info/LICENSE
llm_voice-0.0.1.dist-info/METADATA
llm_voice-0.0.1.dist-info/WHEEL
llm_voice-0.0.1.dist-info/RECORD
