Metadata-Version: 2.1
Name: llm-voice
Version: 0.0.1
Summary: Library to reduce latency in voice generations from LLM chat completion streams
License: MIT
Author: Jake Cyr
Author-email: cyrjake@gmail.com
Requires-Python: >=3.12,<4.0
Classifier: License :: OSI Approved :: MIT License
Classifier: Programming Language :: Python :: 3
Classifier: Programming Language :: Python :: 3.12
Requires-Dist: google-cloud-texttospeech (>=2.14.2,<3.0.0)
Requires-Dist: gtts (>=2.4.0,<3.0.0)
Requires-Dist: ollama (>=0.2.1,<0.3.0)
Requires-Dist: openai (>=1.33.0,<2.0.0)
Requires-Dist: pyaudio (>=0.2.14,<0.3.0)
Requires-Dist: python-dotenv (>=1.0.0,<2.0.0)
